setup.cfg
setup.py
schemavalidator/__init__.py
schemavalidator/schemavalidator.py
schemavalidator.egg-info/PKG-INFO
schemavalidator.egg-info/SOURCES.txt
schemavalidator.egg-info/dependency_links.txt
schemavalidator.egg-info/requires.txt
schemavalidator.egg-info/top_level.txt