Metadata-Version: 1.1
Name: schemavalidator
Version: 0.1.0b12
Summary: A local JSON schema validator based on jsonschema
Home-page: https://github.com/wendbv/schemavalidator
Author: Daan Porru (Wend)
Author-email: daan@wend.nl
License: MIT
Keywords: json schema,validator
Platform: UNKNOWN
Classifier: Development Status :: 4 - Beta
Classifier: Programming Language :: Python :: 3.5
